{
    "id": "eventTypeCondition",
    "tags": [ "event", "eventCondition" ],
    "parentCondition" : {
        "type": "eventPropertyCondition",
        "parameterValues": {
            "propertyName": "eventType",
            "propertyValue": "parameter::eventTypeId",
            "comparisonOperator": "equals"
        }
    },
    "parameters": [
        {
            "id": "eventTypeId",
            "type": "String",
            "multivalued": false,
            "choiceListInitializerFilter": "(initializerId=eventTypeId)"
        }
    ]
}