{
    "metadata": {
        "id": "youngRich",
        "name": "Young rich",
        "scope": "ACMESPACE",
        "description": "This segment includes all young rich"
    },
    "condition": {
        "parameterValues": {
            "subConditions": [
                {
                    "parameterValues": {
                        "propertyName": "properties.age",
                        "propertyValue": 25,
                        "comparisonOperator": "lessThan"
                    },
                    "type": "userPropertyCondition"
                },
                {
                    "parameterValues": {
                        "propertyName": "properties.income",
                        "propertyValue": 10000000,
                        "comparisonOperator": "greaterThan"
                    },
                    "type": "userPropertyCondition"
                }
            ]
        },
        "type": "andCondition"
    }
}