{
    "metadata": {
        "id": "_88q0q11x7_downloadGoalTest",
        "name": "Download Goal Test",
        "scope": "ACMESPACE",
        "description": "Download Goal : download banner-earth.png on home page",
        "tags":["downloadGoal"]
    },
    "startEvent": {
        "parameterValues": {
            "pagePath": "/sites/ACMESPACE/home"
        },
        "type": "pageViewEventCondition"
    },
    "targetEvent": {
        "parameterValues": {
            "filePath": "/sites/ACMESPACE/files/Images/Banner-home-slider/banner-earth.png"
        },
        "type": "downloadEventCondition"
    }
}
